AUTHORS.rst
CONTRIBUTING.rst
HISTORY.rst
LICENSE
MANIFEST.in
README.rst
setup.cfg
setup.py
brotation/__init__.py
brotation/brotation.py
brotation/cli.py
brotation.egg-info/PKG-INFO
brotation.egg-info/SOURCES.txt
brotation.egg-info/dependency_links.txt
brotation.egg-info/entry_points.txt
brotation.egg-info/not-zip-safe
brotation.egg-info/requires.txt
brotation.egg-info/top_level.txt
docs/Makefile
docs/authors.rst
docs/conf.py
docs/contributing.rst
docs/history.rst
docs/index.rst
docs/installation.rst
docs/make.bat
docs/readme.rst
docs/usage.rst
tests/.coverage
tests/__init__.py
tests/application.log
tests/brotation.log
tests/ci.sh
tests/stm.log
tests/test.log
tests/test_brotation.py
tests/test_rotation.py
tests/htmlcov/_home_agp_Documents_me_code_brotation_brotation___init___py.html
tests/htmlcov/_home_agp_Documents_me_code_brotation_brotation_brotation_py.html
tests/htmlcov/_home_agp_Documents_me_code_brotation_brotation_cli_py.html
tests/htmlcov/coverage_html.js
tests/htmlcov/index.html
tests/htmlcov/jquery.ba-throttle-debounce.min.js
tests/htmlcov/jquery.hotkeys.js
tests/htmlcov/jquery.isonscreen.js
tests/htmlcov/jquery.min.js
tests/htmlcov/jquery.tablesorter.min.js
tests/htmlcov/keybd_closed.png
tests/htmlcov/keybd_open.png
tests/htmlcov/status.json
tests/htmlcov/style.css