Metadata-Version: 1.2
Name: brotation
Version: 0.1.3
Summary: Compress and rotate files.
Home-page: https://github.com/asterio.gonzalez/brotation
Author: Asterio Gonzalez
Author-email: asterio@protonmail.com
License: MIT license
Keywords: brotation
Platform: UNKNOWN
Classifier: Development Status :: 2 - Pre-Alpha
Classifier: Intended Audience :: Developers
Classifier: License :: OSI Approved :: MIT License
Classifier: Natural Language :: English
Classifier: Programming Language :: Python :: 3
Classifier: Programming Language :: Python :: 3.5
Classifier: Programming Language :: Python :: 3.6
Classifier: Programming Language :: Python :: 3.7
Classifier: Programming Language :: Python :: 3.8
Requires-Python: >=3.5
